plot2llm/__init__.py
plot2llm/converter.py
plot2llm/domain_knowledge.py
plot2llm/formatters.py
plot2llm/utils.py
plot2llm/analyzers/__init__.py
plot2llm/analyzers/bar_analyzer.py
plot2llm/analyzers/base_analyzer.py
plot2llm/analyzers/histogram_analyzer.py
plot2llm/analyzers/line_analyzer.py
plot2llm/analyzers/matplotlib_analyzer.py
plot2llm/analyzers/scatter_analyzer.py
plot2llm/analyzers/seaborn_analyzer.py
plot2llm/sections/axes_section.py
plot2llm/sections/data_summary_section.py
plot2llm/sections/domain_context_section.py
plot2llm/sections/layout_section.py
plot2llm/sections/llm_context_section.py
plot2llm/sections/llm_description_section.py
plot2llm/sections/metadata_section.py
plot2llm/sections/pattern_analysis_section.py
plot2llm/sections/section_factory.py
plot2llm/sections/statistical_insights_section.py
plot2llm/sections/visual_elements_section.py
plot2llm-0.2.2.dist-info/METADATA
plot2llm-0.2.2.dist-info/WHEEL
plot2llm-0.2.2.dist-info/licenses/LICENSE
plot2llm-0.2.2.dist-info/RECORD
