Metadata-Version: 2.4
Name: plot2llm
Version: 0.2.2
Summary: Convert figures from visualization libraries into formats optimized for Large Language Models (LLMs)
Project-URL: Homepage, https://github.com/Osc2405/plot2llm
Project-URL: Documentation, https://plot2llm.readthedocs.io
Project-URL: Repository, https://github.com/Osc2405/plot2llm.git
Project-URL: Bug Tracker, https://github.com/Osc2405/plot2llm/issues
Project-URL: Source Code, https://github.com/Osc2405/plot2llm
Project-URL: Download, https://pypi.org/project/plot2llm/#files
Author-email: Osc2405 <orosero2405@gmail.com>
Maintainer-email: Osc2405 <orosero2405@gmail.com>
License: MIT
License-File: LICENSE
Keywords: data-analysis,llm,machine-learning,matplotlib,plotly,seaborn,visualization
Classifier: Development Status :: 4 - Beta
Classifier: Intended Audience :: Developers
Classifier: Intended Audience :: Science/Research
Classifier: License :: OSI Approved :: MIT License
Classifier: Operating System :: OS Independent
Classifier: Programming Language :: Python :: 3
Classifier: Programming Language :: Python :: 3.8
Classifier: Programming Language :: Python :: 3.9
Classifier: Programming Language :: Python :: 3.10
Classifier: Programming Language :: Python :: 3.11
Classifier: Programming Language :: Python :: 3.12
Classifier: Programming Language :: Python :: 3.13
Classifier: Topic :: Scientific/Engineering :: Information Analysis
Classifier: Topic :: Scientific/Engineering :: Visualization
Classifier: Topic :: Software Development :: Libraries :: Python Modules
Requires-Python: >=3.8
Requires-Dist: jsonschema>=3.2.0
Requires-Dist: matplotlib>=3.3.0
Requires-Dist: numpy>=1.19.0
Requires-Dist: pandas>=1.1.0
Requires-Dist: scipy>=1.7.0
Requires-Dist: seaborn>=0.11.0
Requires-Dist: webcolors>=1.11.0
Provides-Extra: all
Requires-Dist: plotly>=4.14.0; extra == 'all'
Provides-Extra: dev
Requires-Dist: black>=21.0.0; extra == 'dev'
Requires-Dist: flake8>=3.8.0; extra == 'dev'
Requires-Dist: isort>=5.10.0; extra == 'dev'
Requires-Dist: mypy>=0.800; extra == 'dev'
Requires-Dist: pre-commit>=2.15.0; extra == 'dev'
Requires-Dist: pytest-cov>=2.10.0; extra == 'dev'
Requires-Dist: pytest>=6.0.0; extra == 'dev'
Provides-Extra: docs
Requires-Dist: myst-parser>=0.15.0; extra == 'docs'
Requires-Dist: sphinx-rtd-theme>=1.0.0; extra == 'docs'
Requires-Dist: sphinx>=4.0.0; extra == 'docs'
Provides-Extra: matplotlib
Requires-Dist: matplotlib>=3.3.0; extra == 'matplotlib'
Provides-Extra: plotly
Requires-Dist: plotly>=4.14.0; extra == 'plotly'
Provides-Extra: seaborn
Requires-Dist: seaborn>=0.11.0; extra == 'seaborn'
Provides-Extra: test
Requires-Dist: matplotlib>=3.3.0; extra == 'test'
Requires-Dist: plotly>=4.14.0; extra == 'test'
Requires-Dist: pytest-cov>=2.10.0; extra == 'test'
Requires-Dist: pytest>=6.0.0; extra == 'test'
Requires-Dist: seaborn>=0.11.0; extra == 'test'
